vswobbly/__init__.py
vswobbly/_metadata.py
vswobbly/types.py
vswobbly/util.py
vswobbly/components/__init__.py
vswobbly/components/combed.py
vswobbly/components/custom_lists.py
vswobbly/components/decimations.py
vswobbly/components/freeze.py
vswobbly/components/ifades.py
vswobbly/components/matches.py
vswobbly/components/orphans.py
vswobbly/components/presets.py
vswobbly/components/sections.py
vswobbly/components/types.py
vswobbly/components/video.py
vswobbly/data/__init__.py
vswobbly/data/builder.py
vswobbly/data/parse.py
vswobbly/data/validation.py
vswobbly/exceptions/__init__.py
vswobbly/exceptions/frame.py
vswobbly/exceptions/match.py
vswobbly/exceptions/wobbly.py
vswobbly/process/__init__.py
vswobbly/process/processor.py
vswobbly/process/strategies/__init__.py
vswobbly/process/strategies/abstract.py
vswobbly/process/strategies/base.py
vswobbly/process/strategies/combed.py
vswobbly/process/strategies/custom_lists.py
vswobbly/process/strategies/ifades.py
vswobbly/process/strategies/orphans.py
vswobbly-0.2.0.dist-info/licenses/LICENSE
vswobbly-0.2.0.dist-info/METADATA
vswobbly-0.2.0.dist-info/WHEEL
vswobbly-0.2.0.dist-info/top_level.txt
vswobbly-0.2.0.dist-info/RECORD
